glue_genes/__init__.py
glue_genes/glue_genomics_data/__init__.py
glue_genes/glue_genomics_data/bed_factory.py
glue_genes/glue_genomics_data/bigwig_factory.py
glue_genes/glue_genomics_data/geojson_factory.py
glue_genes/glue_genomics_data/image_link_functions.py
glue_genes/glue_genomics_data/multires_data.py
glue_genes/glue_genomics_data/ome_zarr_factory.py
glue_genes/glue_genomics_data/openslide_factory.py
glue_genes/glue_genomics_data/spaceranger_factory.py
glue_genes/glue_genomics_data/tifffile_factory.py
glue_genes/glue_genomics_data/zarr_factory.py
glue_genes/glue_single_cell/__init__.py
glue_genes/glue_single_cell/anndata_factory.py
glue_genes/glue_single_cell/component.py
glue_genes/glue_single_cell/data.py
glue_genes/glue_single_cell/menubar_plugin.py
glue_genes/glue_single_cell/state.py
glue_genes/glue_single_cell/qt/__init__.py
glue_genes/glue_single_cell/qt/diff_gene_exp.py
glue_genes/glue_single_cell/qt/diff_gene_exp.ui
glue_genes/glue_single_cell/qt/enrichr.py
glue_genes/glue_single_cell/qt/enrichr.ui
glue_genes/glue_single_cell/qt/load_data.py
glue_genes/glue_single_cell/qt/load_data.ui
glue_genes/glue_single_cell/qt/summarize_gene_subset.py
glue_genes/glue_single_cell/qt/summarize_gene_subset.ui
glue_genes/glue_single_cell/qt/tests/__init__.py
glue_genes/glue_single_cell/qt/tests/test_data_load.py
glue_genes/glue_single_cell/qt/tests/test_diff_gene_exp.py
glue_genes/glue_single_cell/qt/tests/test_enrichr.py
glue_genes/glue_single_cell/qt/tests/test_summarize_gene_subset.py
glue_genes/glue_single_cell/qt/tests/data/__init__.py
glue_genes/glue_single_cell/qt/tests/data/test_data.h5ad
glue_genes/glue_single_cell/qt/tests/data/test_data_compressed.h5ad
glue_genes/glue_single_cell/qt/tests/data/test_data_dense.h5ad
glue_genes/glue_single_cell/qt/tests/data/test_data_dense_compressed.h5ad
glue_genes/glue_single_cell/qt/tests/data/test_other_data.h5ad
glue_genes/glue_single_cell/qtl_viewer/__init__.py
glue_genes/glue_single_cell/qtl_viewer/layer_artist.py
glue_genes-1.2.3.dist-info/LICENSE
glue_genes-1.2.3.dist-info/METADATA
glue_genes-1.2.3.dist-info/WHEEL
glue_genes-1.2.3.dist-info/entry_points.txt
glue_genes-1.2.3.dist-info/top_level.txt
glue_genes-1.2.3.dist-info/RECORD
